LICENSE.txt
MANIFEST.in
README.rst
requirements.txt
setup.py
docs/dashboard_preview.png
docs/metadata_workflow.md
docs/usage.md
xfcs/FCS.py
xfcs/__init__.py
xfcs/commands.py
xfcs/get_data.py
xfcs/get_metadata.py
xfcs/version.py
xfcs.egg-info/PKG-INFO
xfcs.egg-info/SOURCES.txt
xfcs.egg-info/dependency_links.txt
xfcs.egg-info/entry_points.txt
xfcs.egg-info/requires.txt
xfcs.egg-info/top_level.txt
xfcs/FCSFile/DataSection.py
xfcs/FCSFile/FCSError.py
xfcs/FCSFile/FCSFile.py
xfcs/FCSFile/Metadata.py
xfcs/FCSFile/ParameterData.py
xfcs/FCSFile/__init__.py
xfcs/FCSFile/validate.py
xfcs/utils/__init__.py
xfcs/utils/locator.py
xfcs/utils/metadata_csv.py
xfcs/utils/metadata_plot.py
xfcs/utils/metadata_stats.py
xfcs/utils/metadata_time.py