Metadata-Version: 1.2
Name: xfcs
Version: 1.1.6
Summary: Extract Flow Cytometry data from FCS files version 3+.
Home-page: https://github.com/j4c0bs/xfcs
Author: Jeremy Jacobs
Author-email: pub@j4c0bs.net
License: BSD
Keywords: FCS FCS3.0 FCS3.1 flow cytometry
Platform: UNKNOWN
Classifier: Environment :: Console
Classifier: Intended Audience :: Developers
Classifier: Intended Audience :: End Users/Desktop
Classifier: Intended Audience :: Science/Research
Classifier: License :: OSI Approved :: BSD License
Classifier: Operating System :: OS Independent
Classifier: Topic :: Scientific/Engineering
Classifier: Topic :: Scientific/Engineering :: Bio-Informatics
Classifier: Programming Language :: Python :: 3.5
Classifier: Programming Language :: Python :: 3.6
Classifier: Topic :: Utilities
Requires-Python: >3.5
